LICENSE
README.md
pyproject.toml
setup.cfg
setup.py
lyncs_io/__init__.py
lyncs_io/archive.py
lyncs_io/base.py
lyncs_io/convert.py
lyncs_io/dask_io.py
lyncs_io/decomposition.py
lyncs_io/format.py
lyncs_io/formats.py
lyncs_io/hdf5.py
lyncs_io/header.py
lyncs_io/lib.py
lyncs_io/lime.py
lyncs_io/mpi_io.py
lyncs_io/numpy.py
lyncs_io/openqcd.py
lyncs_io/tar.py
lyncs_io/testing.py
lyncs_io/utils.py
lyncs_io.egg-info/PKG-INFO
lyncs_io.egg-info/SOURCES.txt
lyncs_io.egg-info/dependency_links.txt
lyncs_io.egg-info/requires.txt
lyncs_io.egg-info/top_level.txt
lyncs_io/include/openqcd.h