Metadata-Version: 2.1
Name: lyncs-io
Version: 0.2.2
Summary: I/O functions for Python and LQCD file formats
Home-page: https://github.com/Lyncs-API/lyncs.io
Author: Simone Bacchio
Author-email: s.bacchio@gmail.com
License: UNKNOWN
Project-URL: Source, https://github.com/Lyncs-API/lyncs.io
Project-URL: Documentation, https://github.com/Lyncs-API/lyncs.io/README.md
Project-URL: Tracker, https://github.com/Lyncs-API/lyncs.io/issues
Project-URL: Download, https://github.com/Lyncs-API/lyncs.io/archive/master.zip
Keywords: formats,functions,I/O,Python,LQCD
Platform: UNKNOWN
Classifier: Development Status :: 1 - Planning
Classifier: Intended Audience :: Developers
Classifier: Natural Language :: English
Classifier: Programming Language :: Python :: 3 :: Only
Classifier: Intended Audience :: Science/Research
Classifier: License :: OSI Approved :: BSD License
Classifier: Topic :: Scientific/Engineering :: Physics
Classifier: Intended Audience :: Education
Classifier: Operating System :: Unix
Provides-Extra: tree
Provides-Extra: dill
Provides-Extra: hdf5
Provides-Extra: mpi
Provides-Extra: dask
Provides-Extra: openqcd
Provides-Extra: test
Provides-Extra: all
License-File: LICENSE
